mono_banking/__init__.py
mono_banking/_base_client.py
mono_banking/_client.py
mono_banking/_compat.py
mono_banking/_constants.py
mono_banking/_exceptions.py
mono_banking/_files.py
mono_banking/_models.py
mono_banking/_qs.py
mono_banking/_resource.py
mono_banking/_response.py
mono_banking/_streaming.py
mono_banking/_types.py
mono_banking/_version.py
mono_banking/py.typed
mono_banking/_utils/__init__.py
mono_banking/_utils/_logs.py
mono_banking/_utils/_proxy.py
mono_banking/_utils/_streams.py
mono_banking/_utils/_sync.py
mono_banking/_utils/_transform.py
mono_banking/_utils/_typing.py
mono_banking/_utils/_utils.py
mono_banking/lib/.keep
mono_banking/resources/__init__.py
mono_banking/resources/banks.py
mono_banking/resources/collection_intents.py
mono_banking/resources/accounts/__init__.py
mono_banking/resources/accounts/accounts.py
mono_banking/resources/accounts/balances.py
mono_banking/resources/cards/__init__.py
mono_banking/resources/cards/cards.py
mono_banking/resources/cards/look.py
mono_banking/resources/cards/prepaid/__init__.py
mono_banking/resources/cards/prepaid/balance.py
mono_banking/resources/cards/prepaid/operations.py
mono_banking/resources/cards/prepaid/prepaid.py
mono_banking/resources/collection_links/__init__.py
mono_banking/resources/collection_links/collection_links.py
mono_banking/resources/collection_links/intents.py
mono_banking/resources/ledger/__init__.py
mono_banking/resources/ledger/account_holders.py
mono_banking/resources/ledger/ledger.py
mono_banking/resources/ledger/accounts/__init__.py
mono_banking/resources/ledger/accounts/accounts.py
mono_banking/resources/ledger/accounts/balance.py
mono_banking/resources/ledger/accounts/balances.py
mono_banking/resources/ledger/accounts/transactions.py
mono_banking/resources/ledger/tenant/__init__.py
mono_banking/resources/ledger/tenant/config.py
mono_banking/resources/ledger/tenant/tenant.py
mono_banking/resources/spending_controls/__init__.py
monobanking_client-0.0.1a0.dist-info/METADATA
monobanking_client-0.0.1a0.dist-info/WHEEL
monobanking_client-0.0.1a0.dist-info/licenses/LICENSE
monobanking_client-0.0.1a0.dist-info/RECORD
